Metadata-Version: 1.1
Name: uModbus
Version: 1.0.4
Summary: Implementation of the Modbus protocol in pure Python.
Home-page: https://github.com/AdvancedClimateSystems/umodbus/
Author: Auke Willem Oosterhoff
Author-email: a.oosterhoff@climotion.com
License: MPL
Platform: UNKNOWN
Classifier: Development Status :: 6 - Mature
Classifier: Intended Audience :: Developers
Classifier: License :: OSI Approved :: Mozilla Public License 2.0 (MPL 2.0)
Classifier: Operating System :: OS Independent
Classifier: Programming Language :: Python :: 2.7
Classifier: Programming Language :: Python :: 3.4
Classifier: Programming Language :: Python :: 3.5
Classifier: Programming Language :: Python :: 3.6
Classifier: Programming Language :: Python :: 3.7
Classifier: Programming Language :: Python :: 3.8
Classifier: Topic :: Software Development :: Embedded Systems
